finbourne_insights/__init__.py
finbourne_insights/api/__init__.py
finbourne_insights/api/access_evaluations_api.py
finbourne_insights/api/application_metadata_api.py
finbourne_insights/api/auditing_api.py
finbourne_insights/api/candela_traces_api.py
finbourne_insights/api/requests_api.py
finbourne_insights/api/vendor_logs_api.py
finbourne_insights/api_client.py
finbourne_insights/api_response.py
finbourne_insights/configuration.py
finbourne_insights/exceptions.py
finbourne_insights/extensions/__init__.py
finbourne_insights/extensions/api_client.py
finbourne_insights/extensions/api_client_factory.py
finbourne_insights/extensions/api_configuration.py
finbourne_insights/extensions/configuration_loaders.py
finbourne_insights/extensions/configuration_options.py
finbourne_insights/extensions/file_access_token.py
finbourne_insights/extensions/proxy_config.py
finbourne_insights/extensions/refreshing_token.py
finbourne_insights/extensions/rest.py
finbourne_insights/extensions/retry.py
finbourne_insights/extensions/socket_keep_alive.py
finbourne_insights/extensions/tcp_keep_alive_connector.py
finbourne_insights/models/__init__.py
finbourne_insights/models/access_controlled_action.py
finbourne_insights/models/access_controlled_resource.py
finbourne_insights/models/access_evaluation_log.py
finbourne_insights/models/action_id.py
finbourne_insights/models/audit_data.py
finbourne_insights/models/audit_data_summary.py
finbourne_insights/models/audit_entry.py
finbourne_insights/models/audit_entry_note.py
finbourne_insights/models/audit_process.py
finbourne_insights/models/audit_process_summary.py
finbourne_insights/models/bucket.py
finbourne_insights/models/create_audit_entry.py
finbourne_insights/models/histogram.py
finbourne_insights/models/id_selector_definition.py
finbourne_insights/models/identifier_part_schema.py
finbourne_insights/models/link.py
finbourne_insights/models/lusid_problem_details.py
finbourne_insights/models/lusid_validation_problem_details.py
finbourne_insights_sdk-2.3.1.dist-info/METADATA
finbourne_insights_sdk-2.3.1.dist-info/WHEEL
finbourne_insights_sdk-2.3.1.dist-info/RECORD
